MANIFEST.in
README.rst
setup.py
botium/__init__.py
botium/actions.py
botium/areas.py
botium/bots.py
botium/conditions.py
botium/config.py
botium/entities.py
botium/intents.py
botium/nlp.py
botium/signals.py
botium/utils.py
botium.egg-info/PKG-INFO
botium.egg-info/SOURCES.txt
botium.egg-info/dependency_links.txt
botium.egg-info/not-zip-safe
botium.egg-info/top_level.txt