Metadata-Version: 1.1
Name: botium
Version: 1.0.1
Summary: ChatBot Building Framework for Python
Home-page: http://github.com/botium/botium
Author: Deniss Stepanovs
Author-email: bellatrics@gmail.com
License: Apache 2.0
Platform: UNKNOWN
Classifier: Topic :: Scientific/Engineering :: Human Machine Interfaces
Classifier: Framework :: Robot Framework
Classifier: Topic :: Text Processing :: Linguistic
Classifier: Topic :: Software Development :: Libraries :: Python Modules
Classifier: Programming Language :: Python :: 3.5
Classifier: License :: OSI Approved :: Apache Software License
